CHANGELOG.rst
MANIFEST.in
README.rst
release.nix
requirements.nix
requirements.txt
setup.cfg
setup.nix
setup.py
tox.ini
docs/conf.py
docs/index.rst
docs/usage.rst
docs/_static/sphinxcontrib-httpexample.css
docs/_static/sphinxcontrib-httpexample.js
src/sphinxcontrib/__init__.py
src/sphinxcontrib/httpexmpl/__init__.py
src/sphinxcontrib/httpexmpl/builders.py
src/sphinxcontrib/httpexmpl/directives.py
src/sphinxcontrib/httpexmpl/parsers.py
src/sphinxcontrib/httpexmpl/utils.py
src/sphinxcontrib/httpexmpl/static/sphinxcontrib-httpexample.css
src/sphinxcontrib/httpexmpl/static/sphinxcontrib-httpexample.js
src/sphinxcontrib_httpexmpl.egg-info/PKG-INFO
src/sphinxcontrib_httpexmpl.egg-info/SOURCES.txt
src/sphinxcontrib_httpexmpl.egg-info/dependency_links.txt
src/sphinxcontrib_httpexmpl.egg-info/namespace_packages.txt
src/sphinxcontrib_httpexmpl.egg-info/not-zip-safe
src/sphinxcontrib_httpexmpl.egg-info/requires.txt
src/sphinxcontrib_httpexmpl.egg-info/top_level.txt
tests/__init__.py
tests/test_builders.py
tests/test_directives.py
tests/test_fixtures.py
tests/test_parsers.py
tests/test_utils.py
tests/fixtures/001.request.txt
tests/fixtures/001.response.txt
tests/fixtures/002.request.txt
tests/fixtures/002.response.txt
tests/fixtures/003.request.txt
tests/fixtures/003.response.txt
tests/fixtures/004.request.txt
tests/fixtures/004.response.txt
tests/fixtures/005.request.txt
tests/fixtures/005.response.txt
tests/fixtures/006.request.txt
tests/fixtures/006.response.txt
tests/fixtures/007.request.txt
tests/fixtures/007.response.txt
tests/fixtures/008.request.txt
tests/fixtures/009.request.txt
tests/fixtures/010.request.txt
tests/snapshots/__init__.py
tests/snapshots/snap_test_builders.py