Metadata-Version: 1.1
Name: sphinxcontrib-httpexmpl
Version: 0.9.13
Summary: float fix, for temporary use only. original https://github.com/collective/sphinxcontrib-httpexample
Home-page: https://github.com/collective/sphinxcontrib-httpexample
Author: Asko Soukka (plus patches)
Author-email: UNKNOWN
License: GPL version 2
Platform: UNKNOWN
Classifier: Development Status :: 4 - Beta
Classifier: Environment :: Console
Classifier: Environment :: Web Environment
Classifier: Framework :: Sphinx :: Extension
Classifier: Intended Audience :: Developers
Classifier: License :: OSI Approved :: GNU General Public License v2 (GPLv2)
Classifier: Operating System :: OS Independent
Classifier: Programming Language :: Python :: 2
Classifier: Programming Language :: Python :: 3
Classifier: Topic :: Documentation
Classifier: Topic :: Utilities
